HISTORY.txt
README.rst
bootstrap.py
buildout.cfg
setup.py
src/collective/__init__.py
src/collective.zombiedoctesting.egg-info/PKG-INFO
src/collective.zombiedoctesting.egg-info/SOURCES.txt
src/collective.zombiedoctesting.egg-info/dependency_links.txt
src/collective.zombiedoctesting.egg-info/namespace_packages.txt
src/collective.zombiedoctesting.egg-info/not-zip-safe
src/collective.zombiedoctesting.egg-info/requires.txt
src/collective.zombiedoctesting.egg-info/top_level.txt
src/collective/zombiedoctesting/__init__.py
src/collective/zombiedoctesting/tests.py