Metadata-Version: 1.0
Name: collective.zombiedoctesting
Version: 1.1.0
Summary: Fast functional JavaScript testing with Zombie.js
Home-page: https://github.com/datakurre/collective.zombiedoctesting/
Author: Asko Soukka
Author-email: asko.soukka@iki.fi
License: GPL
Keywords: corejet pivotal
Platform: UNKNOWN
Classifier: Programming Language :: Python
